[
  {
    "timestamp": "2026-03-20T00:00:08.517587+00:00",
    "question": "Missouri Tigers vs. Miami Hurricanes",
    "condition_id": "0x4491df698adf8d361aacc240a34d12e751f59f35ec1c8f7d8e3c33f4d15e3ba6",
    "end_datetime": "2026-03-20T04:00:00Z",
    "hours_left": 4,
    "result": "NOT_READY",
    "reason": "No AMM price available: Client error '404 Not Found' for url 'https://clob.polymarket.com/price?token_id=57119745575685967285199928059397927736049483010668099282757547539925770571571&side=BUY'\nFor more information check: https://developer.mozilla.org/en-US/docs/Web/HTTP/Status/404",
    "action": "Rescheduled retry in 30min"
  },
  {
    "timestamp": "2026-03-20T00:00:23.223012+00:00",
    "question": "Iowa Hawkeyes vs. Clemson Tigers",
    "condition_id": "0x41eec77b0af2e0ffa40d1abfa0bfb1cb8c4ca6e304ba42f9fffe7291d69db9be",
    "end_datetime": "2026-03-20T04:00:00Z",
    "hours_left": 3.99,
    "best_bid": 0.54,
    "best_ask": 0.55,
    "spread": 0.01,
    "mid": 0.545,
    "portfolio_value": 999,
    "bet_size_usd": 2,
    "result": "ERROR",
    "reason": "Order failed: {'success': False, 'error': \"OrderArgs.__init__() got an unexpected keyword argument 'order_type'\", 'details': {'market_id': '0x41eec77b0af2e0ffa40d1abfa0bfb1cb8c4ca6e304ba42f9fffe7291d69db9be', 'side': 'BUY', 'price': 0.99, 'size_usd': 2}, 'execution_type': 'market_order', 'executed_price': 0.99}",
    "action": "Trade attempt failed"
  },
  {
    "timestamp": "2026-03-20T00:01:51.443970+00:00",
    "question": "Iowa Hawkeyes vs. Clemson Tigers",
    "condition_id": "0x41eec77b0af2e0ffa40d1abfa0bfb1cb8c4ca6e304ba42f9fffe7291d69db9be",
    "end_datetime": "2026-03-20T04:00:00Z",
    "hours_left": 3.97,
    "best_bid": 0.54,
    "best_ask": 0.55,
    "spread": 0.01,
    "mid": 0.545,
    "portfolio_value": 999,
    "bet_size_usd": 2,
    "result": "ERROR",
    "reason": "Order failed: {'success': False, 'error': \"'SignedOrder' object has no attribute 'get'\", 'details': {'market_id': '0x41eec77b0af2e0ffa40d1abfa0bfb1cb8c4ca6e304ba42f9fffe7291d69db9be', 'side': 'BUY', 'price': 0.99, 'size_usd': 2}, 'execution_type': 'market_order', 'executed_price': 0.99}",
    "action": "Trade attempt failed"
  },
  {
    "timestamp": "2026-03-20T00:02:23.266151+00:00",
    "question": "Santa Clara Broncos vs. Kentucky Wildcats",
    "condition_id": "0x1877d73f4f3cb7fc56ac69f4b83dbaebbecefd8390da3b47265ed4cc7df0f80c",
    "end_datetime": "2026-03-20T04:00:00Z",
    "hours_left": 3.96,
    "best_bid": 0.42,
    "best_ask": 0.43,
    "spread": 0.01,
    "mid": 0.425,
    "portfolio_value": 999,
    "bet_size_usd": 2,
    "result": "ERROR",
    "reason": "Order failed: {'success': False, 'error': \"'SignedOrder' object has no attribute 'get'\", 'details': {'market_id': '0x1877d73f4f3cb7fc56ac69f4b83dbaebbecefd8390da3b47265ed4cc7df0f80c', 'side': 'BUY', 'price': 0.99, 'size_usd': 2}, 'execution_type': 'market_order', 'executed_price': 0.99}",
    "action": "Trade attempt failed"
  },
  {
    "timestamp": "2026-03-20T00:30:11.902406+00:00",
    "question": "Missouri Tigers vs. Miami Hurricanes",
    "condition_id": "0x4491df698adf8d361aacc240a34d12e751f59f35ec1c8f7d8e3c33f4d15e3ba6",
    "end_datetime": "2026-03-20T04:00:00Z",
    "hours_left": 3.5,
    "result": "NOT_READY",
    "reason": "No AMM price available: Client error '404 Not Found' for url 'https://clob.polymarket.com/price?token_id=57119745575685967285199928059397927736049483010668099282757547539925770571571&side=BUY'\nFor more information check: https://developer.mozilla.org/en-US/docs/Web/HTTP/Status/404",
    "action": "Rescheduled retry in 30min"
  },
  {
    "timestamp": "2026-03-20T00:40:03.682084+00:00",
    "question": "Missouri Tigers vs. Miami Hurricanes",
    "condition_id": "0x4491df698adf8d361aacc240a34d12e751f51baef01d79d523a4d498baa45fba",
    "end_datetime": "2026-03-20T04:00:00Z",
    "hours_left": 3.33,
    "best_bid": 0.45,
    "best_ask": 0.46,
    "spread": 0.01,
    "mid": 0.455,
    "portfolio_value": 999,
    "bet_size_usd": 2,
    "result": "ERROR",
    "reason": "Order failed: {'success': False, 'error': \"'SignedOrder' object has no attribute 'get'\", 'details': {'market_id': '0x4491df698adf8d361aacc240a34d12e751f51baef01d79d523a4d498baa45fba', 'side': 'BUY', 'price': 0.99, 'size_usd': 2}, 'execution_type': 'market_order', 'executed_price': 0.99}",
    "action": "Trade attempt failed"
  },
  {
    "timestamp": "2026-03-20T00:43:07.215166+00:00",
    "question": "Bucks vs. Jazz",
    "condition_id": "0x9ec1ed93fa88d106c07695d4a21dcdbcc5b70a421686fcedd653cc63bddb14e2",
    "end_datetime": "2026-03-20T01:00:00Z",
    "hours_left": 0.28,
    "best_bid": 0.68,
    "best_ask": 0.69,
    "spread": 0.01,
    "mid": 0.685,
    "portfolio_value": 999,
    "bet_size_usd": 2,
    "result": "ERROR",
    "reason": "Order failed: {'success': False, 'error': \"'SignedOrder' object has no attribute 'get'\", 'details': {'market_id': '0x9ec1ed93fa88d106c07695d4a21dcdbcc5b70a421686fcedd653cc63bddb14e2', 'side': 'BUY', 'price': 0.99, 'size_usd': 2}, 'execution_type': 'market_order', 'executed_price': 0.99}",
    "action": "Trade attempt failed"
  },
  {
    "timestamp": "2026-03-20T00:46:05.912631+00:00",
    "question": "76ers vs. Kings",
    "condition_id": "0xe9e80920d2bfa1d00cf733762371b6102e9aea5df11c35cb10d470b52efcc2aa",
    "end_datetime": "2026-03-20T02:00:00Z",
    "hours_left": 1.23,
    "best_bid": 0.56,
    "best_ask": 0.57,
    "spread": 0.01,
    "mid": 0.565,
    "portfolio_value": 999,
    "bet_size_usd": 2,
    "result": "ERROR",
    "reason": "Order failed: {'success': False, 'error': \"'SignedOrder' object has no attribute 'get'\", 'details': {'market_id': '0xe9e80920d2bfa1d00cf733762371b6102e9aea5df11c35cb10d470b52efcc2aa', 'side': 'BUY', 'price': 0.99, 'size_usd': 2}, 'execution_type': 'market_order', 'executed_price': 0.99}",
    "action": "Trade attempt failed"
  },
  {
    "timestamp": "2026-03-20T00:49:05.728062+00:00",
    "question": "Utah vs. Golden Knights",
    "condition_id": "0x9af82525f62f45127301f661979e00c6de4f40566fadaa43361daa58a1a79941",
    "end_datetime": "2026-03-20T02:00:00Z",
    "hours_left": 1.18,
    "best_bid": 0.45,
    "best_ask": 0.46,
    "spread": 0.01,
    "mid": 0.455,
    "portfolio_value": 999,
    "bet_size_usd": 2,
    "result": "ERROR",
    "reason": "Order failed: {'success': False, 'error': 'PolyApiException[status_code=425, error_message=service not ready]', 'details': {'market_id': '0x9af82525f62f45127301f661979e00c6de4f40566fadaa43361daa58a1a79941', 'side': 'BUY', 'price': 0.99, 'size_usd': 2}, 'execution_type': 'market_order', 'executed_price': 0.99}",
    "action": "Trade attempt failed"
  },
  {
    "timestamp": "2026-03-20T00:52:05.361924+00:00",
    "question": "Iowa Hawkeyes vs. Clemson Tigers",
    "condition_id": "0x41eec77b0af2e0ffa40d1abfa0bfb1cb8c4ca6e304ba42f9fffe7291d69db9be",
    "end_datetime": "2026-03-20T04:00:00Z",
    "hours_left": 3.13,
    "best_bid": 0.54,
    "best_ask": 0.55,
    "spread": 0.01,
    "mid": 0.545,
    "portfolio_value": 999,
    "bet_size_usd": 2,
    "result": "ERROR",
    "reason": "Order failed: {'success': False, 'error': \"PolyApiException[status_code=401, error_message={'error': 'Unauthorized/Invalid api key'}]\", 'details': {'market_id': '0x41eec77b0af2e0ffa40d1abfa0bfb1cb8c4ca6e304ba42f9fffe7291d69db9be', 'side': 'BUY', 'price': 0.99, 'size_usd': 2}, 'execution_type': 'market_order', 'executed_price': 0.99}",
    "action": "Trade attempt failed"
  },
  {
    "timestamp": "2026-03-20T01:00:19.049525+00:00",
    "question": "Missouri Tigers vs. Miami Hurricanes",
    "condition_id": "0x4491df698adf8d361aacc240a34d12e751f59f35ec1c8f7d8e3c33f4d15e3ba6",
    "end_datetime": "2026-03-20T04:00:00Z",
    "hours_left": 2.99,
    "result": "NOT_READY",
    "reason": "No AMM price available: Client error '404 Not Found' for url 'https://clob.polymarket.com/price?token_id=57119745575685967285199928059397927736049483010668099282757547539925770571571&side=BUY'\nFor more information check: https://developer.mozilla.org/en-US/docs/Web/HTTP/Status/404",
    "action": "Rescheduled retry in 30min"
  },
  {
    "timestamp": "2026-03-20T01:00:33.195910+00:00",
    "question": "Missouri Tigers vs. Miami Hurricanes",
    "condition_id": "0x4491df698adf8d361aacc240a34d12e751f59f35ec1c8f7d8e3c33f4d15e3ba6",
    "end_datetime": "2026-03-20T04:00:00Z",
    "hours_left": 2.99,
    "result": "NOT_READY",
    "reason": "No AMM price available: Client error '404 Not Found' for url 'https://clob.polymarket.com/price?token_id=57119745575685967285199928059397927736049483010668099282757547539925770571571&side=BUY'\nFor more information check: https://developer.mozilla.org/en-US/docs/Web/HTTP/Status/404",
    "action": "Rescheduled retry in 30min"
  },
  {
    "timestamp": "2026-03-20T12:00:06.248072+00:00",
    "question": "Will Elon Musk post 320-339 tweets from March 13 to March 20",
    "condition_id": "0xb810ea8d468ab4783ac913dc8fc848bda0981c87dc5c0eb885067159a1edb2e0",
    "end_datetime": "2026-03-20T16:00:00Z",
    "hours_left": 4,
    "best_bid": 0.238,
    "best_ask": 0.247,
    "spread": 0.009,
    "mid": 0.2425,
    "price_range_allowed": "0.4 - 0.85",
    "result": "NO_TRADE",
    "reason": "Mid price 0.242 outside allowed range 0.4-0.85",
    "action": "Skipped"
  },
  {
    "timestamp": "2026-03-20T12:00:20.478634+00:00",
    "question": "Will the price of Bitcoin be above $70,000 on March 20?",
    "condition_id": "0xe2773087291307a65d37e48f19732717829b62c97ba55641ef8eba0ebf2eae70",
    "end_datetime": "2026-03-20T16:00:00Z",
    "hours_left": 3.99,
    "best_bid": 0.7,
    "best_ask": 0.71,
    "spread": 0.01,
    "mid": 0.705,
    "portfolio_value": 999,
    "bet_size_usd": 2,
    "result": "ERROR",
    "reason": "Order failed: {'success': False, 'error': \"PolyApiException[status_code=400, error_message={'error': 'order 0x36470b9a8551f0b09a0bbff297b7309a189fba22687eadd8a48b23d372597898 is invalid. Size (2.89) lower than the minimum: 5'}]\", 'details': {'market_id': '0xe2773087291307a65d37e48f19732717829b62c97ba55641ef8eba0ebf2eae70', 'side': 'BUY', 'price': 0.69, 'size_usd': 2}, 'execution_type': 'market_order', 'executed_price': 0.69}",
    "action": "Trade attempt failed"
  },
  {
    "timestamp": "2026-03-20T12:01:12.619452+00:00",
    "question": "Will the price of Bitcoin be above $70,000 on March 20?",
    "condition_id": "0xe2773087291307a65d37e48f19732717829b62c97ba55641ef8eba0ebf2eae70",
    "end_datetime": "2026-03-20T16:00:00Z",
    "hours_left": 3.98,
    "best_bid": 0.68,
    "best_ask": 0.69,
    "spread": 0.01,
    "mid": 0.685,
    "portfolio_value": 999,
    "bet_size_usd": 3.45,
    "result": "ERROR",
    "reason": "Order failed: {'success': False, 'error': \"PolyApiException[status_code=400, error_message={'error': 'not enough balance / allowance'}]\", 'details': {'market_id': '0xe2773087291307a65d37e48f19732717829b62c97ba55641ef8eba0ebf2eae70', 'side': 'BUY', 'price': 0.67, 'size_usd': 3.45}, 'execution_type': 'market_order', 'executed_price': 0.67}",
    "action": "Trade attempt failed"
  },
  {
    "timestamp": "2026-03-20T13:30:06.371490+00:00",
    "question": "Will SSC Napoli win on 2026-03-20?",
    "condition_id": "0x2caeb2bba32475c540eb9f41c10032a0fab2e22fae844c6ea5064299d8a0b2de",
    "end_datetime": "2026-03-20T17:30:00Z",
    "hours_left": 4,
    "best_bid": 0.55,
    "best_ask": 0.56,
    "spread": 0.01,
    "mid": 0.555,
    "portfolio_value": 999,
    "bet_size_usd": 2.8,
    "shares": 5,
    "order_id": "0x0d932a69d8d8338918417e6f0d8c84ac8d46d33dea7b305f76945da4211ab115",
    "result": "TRADED",
    "reason": "All conditions met \u2014 order placed",
    "action": "BUY 5.0 shares @ 0.56 = $2.80"
  },
  {
    "timestamp": "2026-03-20T13:35:07.047598+00:00",
    "question": "LIU Sharks vs. Arizona Wildcats: O/U 150.5",
    "condition_id": "0xc8445aac2921d4f89ab2a800c387395d1078f0f99b16afb02c91d9ddd0d79397",
    "end_datetime": "2026-03-20T17:35:00Z",
    "hours_left": 4,
    "best_bid": 0.46,
    "best_ask": 0.47,
    "spread": 0.01,
    "mid": 0.465,
    "portfolio_value": 999,
    "bet_size_usd": 2.35,
    "shares": 5,
    "order_id": "0xc17ac91e466e5510defa3bc735593e698f281fb14147f9730cabb940f5e7f0d2",
    "result": "TRADED",
    "reason": "All conditions met \u2014 order placed",
    "action": "BUY 5.0 shares @ 0.47 = $2.35"
  },
  {
    "timestamp": "2026-03-20T13:50:12.597489+00:00",
    "question": "Wright State Raiders vs. Virginia Cavaliers: O/U 145.5",
    "condition_id": "0x50c738ac05f857a2dd6961b88f7922b5e17be633045ddba869ff989c7fc2c105",
    "end_datetime": "2026-03-20T17:50:00Z",
    "hours_left": 4,
    "best_bid": 0.51,
    "best_ask": 0.52,
    "spread": 0.01,
    "mid": 0.515,
    "portfolio_value": 999,
    "bet_size_usd": 2.6,
    "shares": 5,
    "order_id": "0x2edabed32d31d63a79c8bdda7cb7212e8eb9adfee80332af6af80164d88fe6a9",
    "result": "TRADED",
    "reason": "All conditions met \u2014 order placed",
    "action": "BUY 5.0 shares @ 0.52 = $2.60"
  },
  {
    "timestamp": "2026-03-20T16:00:05.121476+00:00",
    "question": "Will Manchester United FC win on 2026-03-20?",
    "condition_id": "0x0629d2ccc609b22b09f2a559967040379d2bb708663e181bc499eda9bec7c7bf",
    "end_datetime": "2026-03-20T20:00:00Z",
    "hours_left": 4,
    "best_bid": 0.46,
    "best_ask": 0.47,
    "spread": 0.01,
    "mid": 0.465,
    "portfolio_value": 999,
    "bet_size_usd": 2.35,
    "shares": 5,
    "order_id": "0x5a8933db45609f40178f560118b76ed7096bbbae737ec6807dc210f3690e9aeb",
    "result": "TRADED",
    "reason": "All conditions met \u2014 order placed",
    "action": "BUY 5.0 shares @ 0.47 = $2.35"
  },
  {
    "timestamp": "2026-03-20T18:00:04.432132+00:00",
    "question": "Counter-Strike: Team Falcons vs Natus Vincere (BO3)",
    "condition_id": "0xbc5c11242d7a45250c286f781104d3ecaf2ece28099b14c03ebb81d7769a5495",
    "end_datetime": "2026-03-20T22:00:00Z",
    "hours_left": 4,
    "best_bid": 0.68,
    "best_ask": 0.69,
    "spread": 0.01,
    "mid": 0.685,
    "portfolio_value": 999,
    "bet_size_usd": 3.45,
    "shares": 5,
    "order_id": "0xa37f5eccd4c1229a343761fe6cb72ec9a6a71ce66020e19d0df64a2035ea2048",
    "result": "TRADED",
    "reason": "All conditions met \u2014 order placed",
    "action": "BUY 5.0 shares @ 0.69 = $3.45"
  },
  {
    "timestamp": "2026-03-20T19:10:05.157348+00:00",
    "question": "Northern Iowa Panthers vs. St. Johns Red Storm: O/U 131.5",
    "condition_id": "0xffea4fee962b35ce91fded250495e846b8220be27daaad61655e3d1d28a4b2e7",
    "end_datetime": "2026-03-20T23:10:00Z",
    "hours_left": 4,
    "best_bid": 0.52,
    "best_ask": 0.53,
    "spread": 0.01,
    "mid": 0.525,
    "portfolio_value": 999,
    "bet_size_usd": 2.65,
    "shares": 5,
    "order_id": "0xc0f0c8a59845088e779cd6c6a8094f39afebf9a1f781117b5d30431309910c78",
    "result": "TRADED",
    "reason": "All conditions met \u2014 order placed",
    "action": "BUY 5.0 shares @ 0.53 = $2.65"
  },
  {
    "timestamp": "2026-03-20T19:25:06.423758+00:00",
    "question": "UCF Knights vs. UCLA Bruins: O/U 151.5",
    "condition_id": "0xc9c6d01c582632407339de8078bcfb03cc0a9932f2f5ab37d7ad6058b595913b",
    "end_datetime": "2026-03-20T23:25:00Z",
    "hours_left": 4,
    "best_bid": 0.5,
    "best_ask": 0.51,
    "spread": 0.01,
    "mid": 0.505,
    "portfolio_value": 999,
    "bet_size_usd": 2.55,
    "shares": 5,
    "order_id": "0xc36d0d05fb2c69941e10097ed949838edb95bfa678ce60745a09a2a19826f909",
    "result": "TRADED",
    "reason": "All conditions met \u2014 order placed",
    "action": "BUY 5.0 shares @ 0.51 = $2.55"
  },
  {
    "timestamp": "2026-03-20T20:00:04.716808+00:00",
    "question": "Trail Blazers vs. Timberwolves",
    "condition_id": "0xca0136d7acc14db3835e40b5d13bc2723ffc7a34a950bef39a2f5a18b07399c3",
    "end_datetime": "2026-03-21T00:00:00Z",
    "hours_left": 4,
    "best_bid": 0.46,
    "best_ask": 0.47,
    "spread": 0.01,
    "mid": 0.465,
    "portfolio_value": 999,
    "bet_size_usd": 2.35,
    "shares": 5,
    "order_id": "0xa02920b7823028b5674f6b969f90f17d14b7fc19cab5b138fb0833fcac4c37b1",
    "result": "TRADED",
    "reason": "All conditions met \u2014 order placed",
    "action": "BUY 5.0 shares @ 0.47 = $2.35"
  },
  {
    "timestamp": "2026-03-20T21:45:09.882366+00:00",
    "question": "California Baptist Lancers vs. Kansas Jayhawks: O/U 138.5",
    "condition_id": "0xb9783de826d7cc5b10cc5248f62a1c347dfd173410e06a5ca93a0340047dca32",
    "end_datetime": "2026-03-21T01:45:00Z",
    "hours_left": 4,
    "best_bid": 0.53,
    "best_ask": 0.55,
    "spread": 0.02,
    "mid": 0.54,
    "portfolio_value": 999,
    "bet_size_usd": 2.75,
    "shares": 5,
    "order_id": "0xe4fea90af5e333900c22b5524e08f3c330f93b837a328d716e36f56503a0bd87",
    "result": "TRADED",
    "reason": "All conditions met \u2014 order placed",
    "action": "BUY 5.0 shares @ 0.55 = $2.75"
  },
  {
    "timestamp": "2026-03-21T10:26:24.347060+00:00",
    "question": "Will Liverpool FC win on 2026-03-21?",
    "condition_id": "0xeff5cd3520341cfaa6fe7943599f92bf33b6e2f21438aa4d5de4bb136b1d49b4",
    "end_datetime": "2026-03-21T12:30:00Z",
    "hours_left": 2.06,
    "best_bid": 0.44,
    "best_ask": 0.45,
    "spread": 0.01,
    "mid": 0.445,
    "portfolio_value": 4.859965,
    "bet_size_usd": 2.25,
    "result": "ERROR",
    "reason": "Order failed: {'success': False, 'error': \"PolyApiException[status_code=400, error_message={'error': 'not enough balance / allowance'}]\", 'details': {'market_id': '0xeff5cd3520341cfaa6fe7943599f92bf33b6e2f21438aa4d5de4bb136b1d49b4', 'side': 'BUY', 'price': 0.44, 'size_usd': 2.25}, 'execution_type': 'market_order', 'executed_price': 0.44}",
    "action": "Trade attempt failed"
  },
  {
    "timestamp": "2026-03-21T10:26:22.918040+00:00",
    "question": "Brighton & Hove Albion FC vs. Liverpool FC: O/U 2.5",
    "condition_id": "0xd40f11784601a47c1a35b37e4da6190b5f34af424a00db5b76d3325593a39ecb",
    "end_datetime": "2026-03-21T12:30:00Z",
    "hours_left": 2.06,
    "best_bid": 0.61,
    "best_ask": 0.62,
    "spread": 0.01,
    "mid": 0.615,
    "portfolio_value": 4.859965,
    "bet_size_usd": 3.1,
    "shares": 5,
    "order_id": "0x4f089ae5c0cf46951ea3c8f73bb49b1154d87d77c657bcbb03729722edd38391",
    "result": "TRADED",
    "reason": "All conditions met \u2014 order placed",
    "action": "BUY 5.0 shares @ 0.62 = $3.10"
  },
  {
    "timestamp": "2026-03-21T10:26:24.433753+00:00",
    "question": "Will Parma Calcio 1913 win on 2026-03-21?",
    "condition_id": "0xf7b1c08539977b987e2d7c03c3c08b48485a108e4874e85f0e284a45d4e7d28e",
    "end_datetime": "2026-03-21T14:00:00Z",
    "hours_left": 3.56,
    "best_bid": 0.43,
    "best_ask": 0.44,
    "spread": 0.01,
    "mid": 0.435,
    "portfolio_value": 4.859965,
    "bet_size_usd": 2.2,
    "result": "ERROR",
    "reason": "Order failed: {'success': False, 'error': \"PolyApiException[status_code=400, error_message={'error': 'not enough balance / allowance'}]\", 'details': {'market_id': '0xf7b1c08539977b987e2d7c03c3c08b48485a108e4874e85f0e284a45d4e7d28e', 'side': 'BUY', 'price': 0.43, 'size_usd': 2.2}, 'execution_type': 'market_order', 'executed_price': 0.43}",
    "action": "Trade attempt failed"
  },
  {
    "timestamp": "2026-03-21T10:26:24.191839+00:00",
    "question": "Will Elche CF win on 2026-03-21?",
    "condition_id": "0xec3b78be60dfa9e0c59b8bb85180ab3426961142cc4dcdb7d035641c7191a94f",
    "end_datetime": "2026-03-21T13:00:00Z",
    "hours_left": 2.56,
    "best_bid": 0.46,
    "best_ask": 0.47,
    "spread": 0.01,
    "mid": 0.465,
    "portfolio_value": 4.859965,
    "bet_size_usd": 2.35,
    "result": "ERROR",
    "reason": "Order failed: {'success': False, 'error': \"PolyApiException[status_code=400, error_message={'error': 'not enough balance / allowance'}]\", 'details': {'market_id': '0xec3b78be60dfa9e0c59b8bb85180ab3426961142cc4dcdb7d035641c7191a94f', 'side': 'BUY', 'price': 0.46, 'size_usd': 2.35}, 'execution_type': 'market_order', 'executed_price': 0.46}",
    "action": "Trade attempt failed"
  },
  {
    "timestamp": "2026-03-21T10:30:03.511651+00:00",
    "question": "Will FC Bayern M\u00fcnchen win on 2026-03-21?",
    "condition_id": "0x8d793cbcf9d9f8f491474a4693428f45155b5f698a5fcb4e25d8f181dd8c1db5",
    "end_datetime": "2026-03-21T14:30:00Z",
    "hours_left": 4,
    "best_bid": 0.84,
    "best_ask": 0.85,
    "spread": 0.01,
    "mid": 0.845,
    "portfolio_value": 27.116068,
    "bet_size_usd": 4.25,
    "result": "ERROR",
    "reason": "Order failed: {'success': False, 'error': \"PolyApiException[status_code=400, error_message={'error': 'not enough balance / allowance'}]\", 'details': {'market_id': '0x8d793cbcf9d9f8f491474a4693428f45155b5f698a5fcb4e25d8f181dd8c1db5', 'side': 'BUY', 'price': 0.84, 'size_usd': 4.25}, 'execution_type': 'market_order', 'executed_price': 0.84}",
    "action": "Trade attempt failed"
  },
  {
    "timestamp": "2026-03-21T10:31:43.632747+00:00",
    "question": "Will Bayer 04 Leverkusen win on 2026-03-21?",
    "condition_id": "0x0c0813604c1983ff930181e24bb69b067655c54a0f3c10e49a281064a1f0cf34",
    "end_datetime": "2026-03-21T14:30:00Z",
    "hours_left": 3.97,
    "best_bid": 0.62,
    "best_ask": 0.63,
    "spread": 0.01,
    "mid": 0.625,
    "portfolio_value": 27.116068,
    "bet_size_usd": 3.15,
    "result": "ERROR",
    "reason": "Order failed: {'success': False, 'error': \"PolyApiException[status_code=400, error_message={'error': 'not enough balance / allowance'}]\", 'details': {'market_id': '0x0c0813604c1983ff930181e24bb69b067655c54a0f3c10e49a281064a1f0cf34', 'side': 'BUY', 'price': 0.62, 'size_usd': 3.15}, 'execution_type': 'market_order', 'executed_price': 0.62}",
    "action": "Trade attempt failed"
  },
  {
    "timestamp": "2026-03-21T10:32:47.940166+00:00",
    "question": "1. FC K\u00f6ln vs. Borussia M\u00f6nchengladbach: O/U 2.5",
    "condition_id": "0xe6cbdc17eaa802f49c704dab3351f2af2f739c63850bb5ab1bd625fbffc52756",
    "end_datetime": "2026-03-21T14:30:00Z",
    "hours_left": 3.95,
    "best_bid": 0.5,
    "best_ask": 0.51,
    "spread": 0.01,
    "mid": 0.505,
    "portfolio_value": 27.116068,
    "bet_size_usd": 2.55,
    "shares": 5,
    "order_id": "0xc21927d8a6eef01a3f79fb86c8e777658817ed2e8fa5aabd446be691fb747d50",
    "result": "TRADED",
    "reason": "All conditions met \u2014 order placed",
    "action": "BUY 5.0 shares @ 0.51 = $2.55"
  },
  {
    "timestamp": "2026-03-21T10:32:59.757344+00:00",
    "question": "Will Parma Calcio 1913 win on 2026-03-21?",
    "condition_id": "0xf7b1c08539977b987e2d7c03c3c08b48485a108e4874e85f0e284a45d4e7d28e",
    "end_datetime": "2026-03-21T14:00:00Z",
    "hours_left": 3.45,
    "best_bid": 0.43,
    "best_ask": 0.44,
    "spread": 0.01,
    "mid": 0.435,
    "portfolio_value": 27.116068,
    "bet_size_usd": 2.2,
    "shares": 5,
    "order_id": "0xf46af80b4e794940406ec2243d42b897f91271e1ee089c3e9916b0f71748e28b",
    "result": "TRADED",
    "reason": "All conditions met \u2014 order placed",
    "action": "BUY 5.0 shares @ 0.44 = $2.20"
  },
  {
    "timestamp": "2026-03-21T10:33:40.660235+00:00",
    "question": "FC Bayern M\u00fcnchen vs. 1. FC Union Berlin: O/U 3.5",
    "condition_id": "0x5d7f390cec7090f342610254851171e57870fdcc78979cf6fd76428ad0b4ff30",
    "end_datetime": "2026-03-21T14:30:00Z",
    "hours_left": 3.94,
    "best_bid": 0.54,
    "best_ask": 0.55,
    "spread": 0.01,
    "mid": 0.545,
    "portfolio_value": 27.116068,
    "bet_size_usd": 2.75,
    "shares": 5,
    "order_id": "0x927d6e6d14ccfc542e46652458c730db5aa8ade73dc43e4ddae8a19e91d7708d",
    "result": "TRADED",
    "reason": "All conditions met \u2014 order placed",
    "action": "BUY 5.0 shares @ 0.55 = $2.75"
  },
  {
    "timestamp": "2026-03-21T10:34:10.690059+00:00",
    "question": "Will Liverpool FC win on 2026-03-21?",
    "condition_id": "0xeff5cd3520341cfaa6fe7943599f92bf33b6e2f21438aa4d5de4bb136b1d49b4",
    "end_datetime": "2026-03-21T12:30:00Z",
    "hours_left": 1.93,
    "best_bid": 0.43,
    "best_ask": 0.44,
    "spread": 0.01,
    "mid": 0.435,
    "portfolio_value": 37.306068,
    "bet_size_usd": 2.2,
    "shares": 5,
    "order_id": "0xce99884e7735fe002db73733a7424c0ae30478432bb66265a984c58bd1266c75",
    "result": "TRADED",
    "reason": "All conditions met \u2014 order placed",
    "action": "BUY 5.0 shares @ 0.44 = $2.20"
  },
  {
    "timestamp": "2026-03-21T11:00:03.313073+00:00",
    "question": "Will Fulham FC win on 2026-03-21?",
    "condition_id": "0xae68634cb01137acbe26e65790f7268a523ee1519601f2576bd7b067c7c9f9da",
    "end_datetime": "2026-03-21T15:00:00Z",
    "hours_left": 4,
    "best_bid": 0.63,
    "best_ask": 0.64,
    "spread": 0.01,
    "mid": 0.635,
    "portfolio_value": 34.956068,
    "bet_size_usd": 3.2,
    "shares": 5,
    "order_id": "0xb4e1e2e0ddd47b6baae96ccd1699cabfa0dd254778e8d27b2129c330b5be04b1",
    "result": "TRADED",
    "reason": "All conditions met \u2014 order placed",
    "action": "BUY 5.0 shares @ 0.64 = $3.20"
  },
  {
    "timestamp": "2026-03-21T11:30:04.435520+00:00",
    "question": "Will FC Twente 65 win on 2026-03-21?",
    "condition_id": "0xba6e735f593b38b1f81315a3dd190b02328873b6d6bc290a7bec059e43b34d89",
    "end_datetime": "2026-03-21T15:30:00Z",
    "hours_left": 4,
    "best_bid": 0.65,
    "best_ask": 0.66,
    "spread": 0.01,
    "mid": 0.655,
    "portfolio_value": 29.312268,
    "bet_size_usd": 3.3,
    "shares": 5,
    "order_id": "0x95c499c230c42335720ad6b023186b275fd995a55d1ea3c61c17ff74852dbaf2",
    "result": "TRADED",
    "reason": "All conditions met \u2014 order placed",
    "action": "BUY 5.0 shares @ 0.66 = $3.30"
  },
  {
    "timestamp": "2026-03-21T12:00:05.032640+00:00",
    "question": "Will Toulouse FC win on 2026-03-21?",
    "condition_id": "0xae9faab2667c0b9eec40124fa18b3038f07217b8b89f71f50c2c31ecdd1c9b88",
    "end_datetime": "2026-03-21T16:00:00Z",
    "hours_left": 4,
    "best_bid": 0.52,
    "best_ask": 0.53,
    "spread": 0.01,
    "mid": 0.525,
    "portfolio_value": 27.114967999999998,
    "bet_size_usd": 2.65,
    "shares": 5,
    "order_id": "0x529e10fb2519994f210708890ba528176128c9b8ce04e134395a9f024344abe7",
    "result": "TRADED",
    "reason": "All conditions met \u2014 order placed",
    "action": "BUY 5.0 shares @ 0.53 = $2.65"
  },
  {
    "timestamp": "2026-03-21T12:00:46.348524+00:00",
    "question": "Will Elon Musk post 90-114 tweets from March 19 to March 21,",
    "condition_id": "0x53d9bfa100ba711e08bcca20564890da16531a4ef3092efd88449bbbe8fbf19c",
    "end_datetime": "2026-03-21T16:00:00Z",
    "hours_left": 3.99,
    "best_bid": 0.08,
    "best_ask": 0.09,
    "spread": 0.01,
    "mid": 0.085,
    "price_range_allowed": "0.4 - 0.85",
    "result": "NO_TRADE",
    "reason": "Mid price 0.085 outside allowed range 0.4-0.85",
    "action": "Skipped"
  },
  {
    "timestamp": "2026-03-21T12:10:03.812087+00:00",
    "question": "Saint Louis Billikens vs. Michigan Wolverines: O/U 161.5",
    "condition_id": "0x57932d42aa4255e3f1f92d844095cb779e2d9b543aa887a5d94c836daef26fa1",
    "end_datetime": "2026-03-21T16:10:00Z",
    "hours_left": 4,
    "best_bid": 0.48,
    "best_ask": 0.49,
    "spread": 0.01,
    "mid": 0.485,
    "portfolio_value": 27.114967999999998,
    "bet_size_usd": 2.45,
    "shares": 5,
    "order_id": "0x3460cc01827217122d4e489bb8bd479e0363c2d15dea1e3fdfde6bb659386e0c",
    "result": "TRADED",
    "reason": "All conditions met \u2014 order placed",
    "action": "BUY 5.0 shares @ 0.49 = $2.45"
  },
  {
    "timestamp": "2026-03-21T12:10:51.005560+00:00",
    "question": "Spread: Michigan Wolverines (-12.5)",
    "condition_id": "0x869af4683bb7f7228b7f05786a9087fe764eba89bc8627c0ee55624827d7053c",
    "end_datetime": "2026-03-21T16:10:00Z",
    "hours_left": 3.99,
    "best_bid": 0.48,
    "best_ask": 0.49,
    "spread": 0.01,
    "mid": 0.485,
    "portfolio_value": 27.114967999999998,
    "bet_size_usd": 2.45,
    "shares": 5,
    "order_id": "0x5cf336f81c8092128db4639be6bb32d28de989d9d558f2f07a0703bfb9a1c17c",
    "result": "TRADED",
    "reason": "All conditions met \u2014 order placed",
    "action": "BUY 5.0 shares @ 0.49 = $2.45"
  },
  {
    "timestamp": "2026-03-21T13:00:06.981706+00:00",
    "question": "Counter-Strike: NIP vs Liquid (BO3) - BLAST Open Rotterdam G",
    "condition_id": "0x686a466ce8cf2d0876d582625023a352c3560d0ec049810f71e31768da0c92f8",
    "end_datetime": "2026-03-21T17:00:00Z",
    "hours_left": 4,
    "best_bid": 0.73,
    "best_ask": 0.75,
    "spread": 0.02,
    "mid": 0.74,
    "portfolio_value": 24.917668,
    "bet_size_usd": 3.75,
    "shares": 5,
    "order_id": "0x632283366e56d9cd679040f58197778f171a9c625aaf255039d96178f6277954",
    "result": "TRADED",
    "reason": "All conditions met \u2014 order placed",
    "action": "BUY 5.0 shares @ 0.75 = $3.75"
  },
  {
    "timestamp": "2026-03-21T13:00:53.208385+00:00",
    "question": "Spread: AC Milan (-1.5)",
    "condition_id": "0x5f67485759ffcf00b33f879456e7ec42834c44f41d25e79a13e3959c7943a088",
    "end_datetime": "2026-03-21T17:00:00Z",
    "hours_left": 3.99,
    "best_bid": 0.45,
    "best_ask": 0.46,
    "spread": 0.01,
    "mid": 0.455,
    "portfolio_value": 21.172767999999998,
    "bet_size_usd": 2.3,
    "shares": 5,
    "order_id": "0xab212649e2a46c20e6d8f28259fd1219f636f4307bbef8504f80cfc9fb1209b0",
    "result": "TRADED",
    "reason": "All conditions met \u2014 order placed",
    "action": "BUY 5.0 shares @ 0.46 = $2.30"
  },
  {
    "timestamp": "2026-03-21T13:01:38.979345+00:00",
    "question": "Jets vs. Penguins",
    "condition_id": "0x246fe77f21c515c84350c40ef9d714b8fea18e7b1fd29bff5801c78c99563013",
    "end_datetime": "2026-03-21T17:00:00Z",
    "hours_left": 3.97,
    "best_bid": 0.4,
    "best_ask": 0.41,
    "spread": 0.01,
    "mid": 0.405,
    "portfolio_value": 21.172767999999998,
    "bet_size_usd": 2.05,
    "shares": 5,
    "order_id": "0xbcbd7a153644f63138205ce478cbe9a8065d1a59d540016a864518f7a567e058",
    "result": "TRADED",
    "reason": "All conditions met \u2014 order placed",
    "action": "BUY 5.0 shares @ 0.41 = $2.05"
  },
  {
    "timestamp": "2026-03-21T13:02:29.964079+00:00",
    "question": "AC Milan vs. Torino FC: O/U 2.5",
    "condition_id": "0x8cd06f2defba65ed11bd6d61ad06e652957992027d51f5393772b15e95f4bfb2",
    "end_datetime": "2026-03-21T17:00:00Z",
    "hours_left": 3.96,
    "best_bid": 0.51,
    "best_ask": 0.52,
    "spread": 0.01,
    "mid": 0.515,
    "portfolio_value": 21.172767999999998,
    "bet_size_usd": 2.6,
    "shares": 5,
    "order_id": "0x50c49fb0e1023302df5d8955aae53f0c24f5b83d98eb7724619825a18fc982cf",
    "result": "TRADED",
    "reason": "All conditions met \u2014 order placed",
    "action": "BUY 5.0 shares @ 0.52 = $2.60"
  },
  {
    "timestamp": "2026-03-21T13:30:04.153789+00:00",
    "question": "Will Chelsea FC win on 2026-03-21?",
    "condition_id": "0xacb2ee285eceaf798ca2c2ffc9c667d7e30dd51d9137de2343dbda2e4e895670",
    "end_datetime": "2026-03-21T17:30:00Z",
    "hours_left": 4,
    "best_bid": 0.43,
    "best_ask": 0.44,
    "spread": 0.01,
    "mid": 0.435,
    "portfolio_value": 19.092768,
    "bet_size_usd": 2.2,
    "shares": 5,
    "order_id": "0xe0efdc307bf8b0eb572d9725ef233d1237b56e4a253fee58fc237c82c43b237e",
    "result": "TRADED",
    "reason": "All conditions met \u2014 order placed",
    "action": "BUY 5.0 shares @ 0.44 = $2.20"
  },
  {
    "timestamp": "2026-03-21T13:30:52.072028+00:00",
    "question": "Will CA Osasuna win on 2026-03-21?",
    "condition_id": "0xf950a9738d53da09f155d60f723d873dd425204b480c2bc78f082be300c0e126",
    "end_datetime": "2026-03-21T17:30:00Z",
    "hours_left": 3.99,
    "best_bid": 0.47,
    "best_ask": 0.48,
    "spread": 0.01,
    "mid": 0.475,
    "portfolio_value": 19.092768,
    "bet_size_usd": 2.4,
    "shares": 5,
    "order_id": "0x681fcfe6f59598a8b7edf92136e5fc0807200ceab3ca1ab301d727d566073ee2",
    "result": "TRADED",
    "reason": "All conditions met \u2014 order placed",
    "action": "BUY 5.0 shares @ 0.48 = $2.40"
  },
  {
    "timestamp": "2026-03-21T15:00:07.196731+00:00",
    "question": "Game Handicap: GEN (-2.5) vs G2 Esports (+2.5)",
    "condition_id": "0x95909d5ecb932da47535310492fcff1ccb2103a49cd278aef24574942655dca9",
    "end_datetime": "2026-03-21T19:00:00Z",
    "hours_left": 4,
    "best_bid": 0,
    "best_ask": 0.001,
    "spread": 0.001,
    "mid": 0.0005,
    "price_range_allowed": "0.4 - 0.85",
    "result": "NO_TRADE",
    "reason": "Mid price 0.001 outside allowed range 0.4-0.85",
    "action": "Skipped"
  },
  {
    "timestamp": "2026-03-21T15:45:03.866457+00:00",
    "question": "Will Juventus FC win on 2026-03-21?",
    "condition_id": "0xdb56955d7c4c40867d4d5203053159f733014119a5366d7fd3224f20bcf248ad",
    "end_datetime": "2026-03-21T19:45:00Z",
    "hours_left": 4,
    "best_bid": 0.75,
    "best_ask": 0.76,
    "spread": 0.01,
    "mid": 0.755,
    "portfolio_value": 4.943068,
    "bet_size_usd": 3.8,
    "result": "ERROR",
    "reason": "Order failed: {'success': False, 'error': \"PolyApiException[status_code=400, error_message={'error': 'not enough balance / allowance'}]\", 'details': {'market_id': '0xdb56955d7c4c40867d4d5203053159f733014119a5366d7fd3224f20bcf248ad', 'side': 'BUY', 'price': 0.75, 'size_usd': 3.8}, 'execution_type': 'market_order', 'executed_price': 0.75}",
    "action": "Trade attempt failed"
  },
  {
    "timestamp": "2026-03-21T16:00:03.872197+00:00",
    "question": "Stars vs. Wild",
    "condition_id": "0xc495e735642f2f1381c60ac15d9146d75835a8e99edac82eaf7f34324a4fbafd",
    "end_datetime": "2026-03-21T20:00:00Z",
    "hours_left": 4,
    "best_bid": 0.55,
    "best_ask": 0.56,
    "spread": 0.01,
    "mid": 0.555,
    "portfolio_value": 4.943068,
    "bet_size_usd": 2.8,
    "result": "ERROR",
    "reason": "Order failed: {'success': False, 'error': \"PolyApiException[status_code=400, error_message={'error': 'not enough balance / allowance'}]\", 'details': {'market_id': '0xc495e735642f2f1381c60ac15d9146d75835a8e99edac82eaf7f34324a4fbafd', 'side': 'BUY', 'price': 0.55, 'size_usd': 2.8}, 'execution_type': 'market_order', 'executed_price': 0.55}",
    "action": "Trade attempt failed"
  },
  {
    "timestamp": "2026-03-21T16:03:04.787918+00:00",
    "question": "Sabres vs. Kings",
    "condition_id": "0x00f6e2dcbdaa165e36668c5b9fa1eabb52665bbfef19fd0444f44d7b429b27d6",
    "end_datetime": "2026-03-21T20:00:00Z",
    "hours_left": 3.95,
    "best_bid": 0.53,
    "best_ask": 0.54,
    "spread": 0.01,
    "mid": 0.535,
    "portfolio_value": 4.943068,
    "bet_size_usd": 2.7,
    "result": "ERROR",
    "reason": "Order failed: {'success': False, 'error': \"PolyApiException[status_code=400, error_message={'error': 'not enough balance / allowance'}]\", 'details': {'market_id': '0x00f6e2dcbdaa165e36668c5b9fa1eabb52665bbfef19fd0444f44d7b429b27d6', 'side': 'BUY', 'price': 0.53, 'size_usd': 2.7}, 'execution_type': 'market_order', 'executed_price': 0.53}",
    "action": "Trade attempt failed"
  },
  {
    "timestamp": "2026-03-21T16:05:11.978314+00:00",
    "question": "Will Paris Saint-Germain FC win on 2026-03-21?",
    "condition_id": "0xab15d465786e8ababf7b91a0b9bbabf3c9d09b49c8f7160f2261f5fc739d094b",
    "end_datetime": "2026-03-21T20:05:00Z",
    "hours_left": 4,
    "best_bid": 0.67,
    "best_ask": 0.68,
    "spread": 0.01,
    "mid": 0.675,
    "portfolio_value": 4.943068,
    "bet_size_usd": 3.4,
    "result": "ERROR",
    "reason": "Order failed: {'success': False, 'error': \"PolyApiException[status_code=400, error_message={'error': 'not enough balance / allowance'}]\", 'details': {'market_id': '0xab15d465786e8ababf7b91a0b9bbabf3c9d09b49c8f7160f2261f5fc739d094b', 'side': 'BUY', 'price': 0.67, 'size_usd': 3.4}, 'execution_type': 'market_order', 'executed_price': 0.67}",
    "action": "Trade attempt failed"
  },
  {
    "timestamp": "2026-03-21T16:06:16.517421+00:00",
    "question": "Spread: Paris Saint-Germain FC (-1.5)",
    "condition_id": "0x95f5a259f0fe7cd259fc52ff56de8123244e2031002505796d533939480a209d",
    "end_datetime": "2026-03-21T20:05:00Z",
    "hours_left": 3.98,
    "best_bid": 0.43,
    "best_ask": 0.45,
    "spread": 0.02,
    "mid": 0.44,
    "portfolio_value": 4.943068,
    "bet_size_usd": 2.25,
    "result": "ERROR",
    "reason": "Order failed: {'success': False, 'error': \"PolyApiException[status_code=400, error_message={'error': 'not enough balance / allowance'}]\", 'details': {'market_id': '0x95f5a259f0fe7cd259fc52ff56de8123244e2031002505796d533939480a209d', 'side': 'BUY', 'price': 0.43, 'size_usd': 2.25}, 'execution_type': 'market_order', 'executed_price': 0.43}",
    "action": "Trade attempt failed"
  },
  {
    "timestamp": "2026-03-21T17:00:05.498989+00:00",
    "question": "Spread: Thunder (-21.5)",
    "condition_id": "0x6d1395537a8a79962f4af149fcf0087a1af0a52e406297dbd8f756d0667a0485",
    "end_datetime": "2026-03-21T21:00:00Z",
    "hours_left": 4,
    "best_bid": 0.47,
    "best_ask": 0.48,
    "spread": 0.01,
    "mid": 0.475,
    "portfolio_value": 4.943068,
    "bet_size_usd": 2.4,
    "result": "ERROR",
    "reason": "Order failed: {'success': False, 'error': \"PolyApiException[status_code=400, error_message={'error': 'not enough balance / allowance'}]\", 'details': {'market_id': '0x6d1395537a8a79962f4af149fcf0087a1af0a52e406297dbd8f756d0667a0485', 'side': 'BUY', 'price': 0.47, 'size_usd': 2.4}, 'execution_type': 'market_order', 'executed_price': 0.47}",
    "action": "Trade attempt failed"
  },
  {
    "timestamp": "2026-03-21T18:10:05.948746+00:00",
    "question": "Spread: Houston Cougars (-9.5)",
    "condition_id": "0x98bc5946ea29e5996fc2900c6a00cbd0690a77220556677169cb2cc518f3d26b",
    "end_datetime": "2026-03-21T22:10:00Z",
    "hours_left": 4,
    "best_bid": 0.53,
    "best_ask": 0.54,
    "spread": 0.01,
    "mid": 0.535,
    "portfolio_value": 10.023068,
    "bet_size_usd": 2.7,
    "shares": 5,
    "order_id": "0x2f66557e58e443db0b6fcd3484cb84c99a69e6c240237778fa7d7b10361fd89a",
    "result": "TRADED",
    "reason": "All conditions met \u2014 order placed",
    "action": "BUY 5.0 shares @ 0.54 = $2.70"
  },
  {
    "timestamp": "2026-03-21T19:00:08.603324+00:00",
    "question": "Lakers vs. Magic",
    "condition_id": "0x0954cc08de0ab8345bcf24f314d571e6a77d913ea9977ce2b4187983a70b450d",
    "end_datetime": "2026-03-21T23:00:00Z",
    "hours_left": 4,
    "best_bid": 0.59,
    "best_ask": 0.6,
    "spread": 0.01,
    "mid": 0.595,
    "portfolio_value": 15.113067999999998,
    "bet_size_usd": 3,
    "shares": 5,
    "order_id": "0x8bf0ae3b8bcaf571b6fc5e042b808f13ed53520713954af8d77c44b3a0ac6746",
    "result": "TRADED",
    "reason": "All conditions met \u2014 order placed",
    "action": "BUY 5.0 shares @ 0.60 = $3.00"
  },
  {
    "timestamp": "2026-03-21T19:01:43.257056+00:00",
    "question": "Lakers vs. Magic: O/U 232.5",
    "condition_id": "0x3daf9ba4c94ed43e577658816f5a6cb3fd8dc22682df5755b6965d2457ce3e73",
    "end_datetime": "2026-03-21T23:00:00Z",
    "hours_left": 3.97,
    "best_bid": 0.51,
    "best_ask": 0.52,
    "spread": 0.01,
    "mid": 0.515,
    "portfolio_value": 15.113067999999998,
    "bet_size_usd": 2.6,
    "shares": 5,
    "order_id": "0x340f9123cdb1f4e71eec061e9d37436a08c142ae188a3f11fdcf886b020e15ab",
    "result": "TRADED",
    "reason": "All conditions met \u2014 order placed",
    "action": "BUY 5.0 shares @ 0.52 = $2.60"
  },
  {
    "timestamp": "2026-03-21T19:02:25.933719+00:00",
    "question": "Cavaliers vs. Pelicans",
    "condition_id": "0x9dbafed5f8865f34fbcba14ac5692428d9fdec3a5cf7127a8afb109f083740dc",
    "end_datetime": "2026-03-21T23:00:00Z",
    "hours_left": 3.96,
    "best_bid": 0.64,
    "best_ask": 0.65,
    "spread": 0.01,
    "mid": 0.645,
    "portfolio_value": 15.113067999999998,
    "bet_size_usd": 3.25,
    "shares": 5,
    "order_id": "0x5c45ff83e6bcbfd113411a1684d131b7c789440e1dbe4b936f5c3a49b21c8eb9",
    "result": "TRADED",
    "reason": "All conditions met \u2014 order placed",
    "action": "BUY 5.0 shares @ 0.65 = $3.25"
  },
  {
    "timestamp": "2026-03-21T19:03:06.639363+00:00",
    "question": "Spread: Lakers (-3.5)",
    "condition_id": "0x726b477b3fc9625d995ad0263c2f6bc2bb07b35231a979870325acaddba5f1e7",
    "end_datetime": "2026-03-21T23:00:00Z",
    "hours_left": 3.95,
    "best_bid": 0.47,
    "best_ask": 0.48,
    "spread": 0.01,
    "mid": 0.475,
    "portfolio_value": 15.113067999999998,
    "bet_size_usd": 2.4,
    "shares": 5,
    "order_id": "0xecf1e703c0e32729770a323361990544379fca78e03942969e201f6eeeca6abd",
    "result": "TRADED",
    "reason": "All conditions met \u2014 order placed",
    "action": "BUY 5.0 shares @ 0.48 = $2.40"
  },
  {
    "timestamp": "2026-03-22T10:16:17.397967+00:00",
    "question": "Will Aston Villa FC win on 2026-03-22?",
    "condition_id": "0xd8e0bd05d6a890ae7cfb4c107aab6282a73ed1d02d65554bc1aeca3106836df5",
    "result": "RESEARCH",
    "match": "Aston Villa vs West Ham United",
    "venue": "Villa Park (HOME)",
    "kickoff": "2026-03-22T14:15:00Z",
    "league_position_villa": 4,
    "league_position_westham": 18,
    "villa_recent_form": "Won 2-0 vs Lille (Europa League)",
    "west_ham_status": "Relegation zone (18th)",
    "market_price_yes": 0.555,
    "confidence_pct": 72,
    "decision": "TRADE",
    "sources_summary": "Sofascore: AV 4th vs WHU 18th @ Villa Park. Structural edge: home top-4 vs relegation side. Market 55.5% underpriced vs ~70% true win prob. Web search unavailable (no Brave API key) but structural edge clear.",
    "reason": "Home 4th-place vs relegation 18th, recent Europa League form, home advantage \u2014 confidence 72% >= 65% threshold, price 0.555 on winning side"
  },
  {
    "timestamp": "2026-03-22T10:16:24.693334+00:00",
    "question": "Will Aston Villa FC win on 2026-03-22?",
    "condition_id": "0xd8e0bd05d6a890ae7cfb4c107aab6282a73ed1d02d65554bc1aeca3106836df5",
    "end_datetime": "2026-03-22T14:15:00Z",
    "hours_left": 3.98,
    "best_bid": 0.55,
    "best_ask": 0.56,
    "spread": 0.01,
    "mid": 0.555,
    "portfolio_value": 31.613367999999998,
    "bet_size_usd": 2.8,
    "shares": 5,
    "order_id": "0x739508acddeff9b09909058a075a04e07499f8f60d30638a1b3a6d42a7266855",
    "confidence_pct": 72,
    "research_summary": "Sofascore: AV 4th vs WHU 18th @ Villa Park. Structural edge: home top-4 vs relegation side. Market 55.5% underpriced vs ~70% true win prob. Web search unavailable (no Brave API key) but structural edge clear.",
    "result": "TRADED",
    "reason": "All conditions met \u2014 order placed",
    "action": "BUY 5.0 shares @ 0.56 = $2.80"
  },
  {
    "timestamp": "2026-03-22T12:01:14.372269+00:00",
    "question": "Texas Tech Red Raiders vs. Alabama Crimson Tide",
    "condition_id": "0x261619a081b347ff183cc4b315647ee98e6645552f65bbeffe15cc83a9d07d26",
    "token_id": "59225215309188916427944200110830336195483543653081163898421203368708527905722",
    "end_datetime": "2026-03-22T16:00:00Z",
    "market_price": 0.515,
    "result": "NO_TRADE",
    "reason": "Confidence below threshold: web_search unavailable (no Brave API key), cannot research injury/lineup/predictions. Structural assessment only yields ~50% confidence vs 65% required threshold. Market price 0.515 suggests coin-flip \u2014 no identified edge.",
    "action": "Skipped"
  },
  {
    "timestamp": "2026-03-22T12:10:00.000000+00:00",
    "question": "Miami Hurricanes vs. Purdue Boilermakers: O/U 147.5",
    "condition_id": "0xc3c777f7bd2f8ba4274e48c116e98f73d9643d46c75dfa9b93b0399bd0f067bb",
    "token_id": "83361458137839236996139699913917418671134082890228643828761181711332456965002",
    "end_datetime": "2026-03-22T16:10:00Z",
    "market_price": 0.525,
    "confidence_pct": 48,
    "result": "NO_TRADE",
    "reason": "Confidence below 65% threshold. Web search unavailable (no Brave API key), all web fetches failed (ESPN/SportsLine/Covers/KenPom returned 403/404). Structural analysis only: Miami FL and Purdue both historically slow-paced, defensive teams \u2014 O/U 147.5 leans UNDER structurally but cannot confirm with pace/injury/expert data. ~48% confidence.",
    "action": "Skipped"
  },
  {
    "timestamp": "2026-03-22T12:22:27.304465+00:00",
    "question": "Will Atalanta BC win on 2026-03-22?",
    "condition_id": "0xdae8a2bcd39b64c42e6d77ac9281660054b1d2d746773387b2dcd928cf34b91c",
    "end_datetime": "2026-03-22T14:00:00Z",
    "hours_left": 1.63,
    "best_bid": 0.7,
    "best_ask": 0.71,
    "spread": 0.01,
    "mid": 0.705,
    "portfolio_value": 28.813868,
    "bet_size_usd": 3.55,
    "shares": 5,
    "order_id": "0xa5213e1c770ff310be5505c3202cf742c79e22747e4067f84dd0792e63ce77b1",
    "confidence_pct": null,
    "research_summary": null,
    "result": "TRADED",
    "reason": "All conditions met \u2014 order placed",
    "action": "BUY 5.0 shares @ 0.71 = $3.55"
  },
  {
    "timestamp": "2026-03-22T14:58:00Z",
    "market": "Tennessee Volunteers vs. Virginia Cavaliers",
    "condition_id": "0xde5ff3427dcc8f53e95d9825721b011458b657837033a6237dc3cfc99777e827",
    "confidence_pct": 67,
    "decision": "TRADE",
    "predicted_winner": "Virginia Cavaliers",
    "polymarket_price": 0.515,
    "sources": [
      "covers.com consensus 62% Virginia",
      "Virginia 30-5 record",
      "Virginia 21/25 ML trend",
      "UVA 97th pct vs post-ups"
    ],
    "red_flags": "NCAA tournament variance; no injury confirmation"
  },
  {
    "timestamp": "2026-03-22T14:59:38.096168+00:00",
    "question": "Tennessee Volunteers vs. Virginia Cavaliers",
    "condition_id": "0xde5ff3427dcc8f53e95d9825721b011458b657837033a6237dc3cfc99777e827",
    "end_datetime": "2026-03-22T16:00:00Z",
    "hours_left": 1.01,
    "best_bid": 0.51,
    "best_ask": 0.52,
    "spread": 0.01,
    "mid": 0.515,
    "portfolio_value": 25.264868,
    "bet_size_usd": 2.6,
    "shares": 5.0,
    "order_id": "0xc1b226fd2552acde0145d4868be636524fe766c5eec2b133dd6131d35c70cd47",
    "confidence_pct": null,
    "research_summary": null,
    "result": "TRADED",
    "reason": "All conditions met \u2014 order placed",
    "action": "BUY 5.0 shares @ 0.52 = $2.60"
  },
  {
    "timestamp": "2026-03-22T15:07:37.194733+00:00",
    "question": "Kentucky Wildcats vs. Iowa State Cyclones: O/U 146.5",
    "condition_id": "0x44dc43de601cf755abe0892523549b14b5837576df3200f002f5588b97ae13a6",
    "end_datetime": "2026-03-22T18:45:00Z",
    "hours_left": 3.62,
    "best_bid": 0.49,
    "best_ask": 0.5,
    "spread": 0.01,
    "mid": 0.495,
    "price_range_allowed": "0.5 - 0.8",
    "result": "NO_TRADE",
    "reason": "Mid price 0.495 outside allowed range 0.5-0.8",
    "action": "Skipped"
  },
  {
    "timestamp": "2026-03-22T15:10:53.702148+00:00",
    "question": "Will Olympique de Marseille win on 2026-03-22?",
    "condition_id": "0x8c11cbf546db17c00f4b1afdb7db3bfac0e5dff3e8ff56211e3854a6472f6a6e",
    "end_datetime": "2026-03-22T16:15:00Z",
    "hours_left": 1.07,
    "best_bid": 0.51,
    "best_ask": 0.52,
    "spread": 0.01,
    "mid": 0.515,
    "portfolio_value": 25.264868,
    "bet_size_usd": 2.6,
    "shares": 5.0,
    "order_id": "0x556caba2510a4ef63831e38cb8cfe643fa2d3c60cada92aeefc074ed5d73f47e",
    "confidence_pct": null,
    "research_summary": null,
    "result": "TRADED",
    "reason": "All conditions met \u2014 order placed",
    "action": "BUY 5.0 shares @ 0.52 = $2.60"
  },
  {
    "timestamp": "2026-03-22T15:20:23.776481+00:00",
    "question": "Avalanche vs. Capitals",
    "condition_id": "0x0c5e51bb81aa30cbe3b598d618a62bbb32f8a79735a35ad0aa51582f074be5d1",
    "end_datetime": "2026-03-22T16:30:00Z",
    "hours_left": 1.16,
    "best_bid": 0.61,
    "best_ask": 0.62,
    "spread": 0.01,
    "mid": 0.615,
    "portfolio_value": 22.668968,
    "bet_size_usd": 3.1,
    "shares": 5.0,
    "order_id": "0xeedcb9f5fc31a9b56e6211df504e868e352cb9bd074ed90afd28ed0d7896be1d",
    "confidence_pct": 68,
    "research_summary": "ESPN data (fresh, 2026-03-22). COL record: 45-13-10 (100pts, 1st Central). WSH record: 35-27-8 (78pts, 5th Metro). COL stats: 3.69 GF/G, 2.46 GA/G. WSH: 3.10 GF/G, 2.84 GA/G. Goaltending: Wedgewood 2.19 GAA/.916 vs Thompson 2.36/.915 (COL advantage). Season series: COL leads 1-0 (won 5-2 Jan 19). Sportsbook ML: COL -162 / WSH +136. MacKinnon 114pts vs Ovechkin 52pts. COL last 5: 2-3 (incl. 7-2 loss to PIT). WSH last 5: 3-2 (home). COL injuries: Lehkonen OUT, O'Connor IR-LT. WSH injuries: Kampf OUT (minor). Brave API unavailable \u2014 no Forebet/Covers/Reddit expert picks obtained.",
    "result": "TRADED",
    "reason": "All conditions met \u2014 order placed",
    "action": "BUY 5.0 shares @ 0.62 = $3.10"
  }
]